gtbook/__init__.py
gtbook/_modidx.py
gtbook/_nbdev.py
gtbook/cli.py
gtbook/dbn.py
gtbook/diffdrive.py
gtbook/discrete.py
gtbook/display.py
gtbook/driving.py
gtbook/drone.py
gtbook/gaussian.py
gtbook/html.py
gtbook/linear.py
gtbook/logistics.py
gtbook/nerf.py
gtbook/stonehenge.py
gtbook/vacuum.py
gtbook-0.0.38.dist-info/LICENSE
gtbook-0.0.38.dist-info/METADATA
gtbook-0.0.38.dist-info/WHEEL
gtbook-0.0.38.dist-info/entry_points.txt
gtbook-0.0.38.dist-info/top_level.txt
gtbook-0.0.38.dist-info/RECORD
