Metadata-Version: 2.1
Name: gtbook
Version: 0.0.38
Summary: Frank Dellaerts book support lib, made with nbdev
Home-page: https://github.com/gtbook/gtbook/tree/master/
Author: Frank Dellaert
Author-email: dellaert@gmail.com
License: Apache Software License 2.0
Keywords: python,nbdev
Classifier: Development Status :: 3 - Alpha
Classifier: Intended Audience :: Developers
Classifier: Natural Language :: English
Classifier: Programming Language :: Python :: 3.9
Classifier: Programming Language :: Python :: 3.10
Classifier: License :: OSI Approved :: Apache Software License
Requires-Python: >=3.9
License-File: LICENSE
Requires-Dist: gtsam >=4.2
Requires-Dist: requests
Requires-Dist: kaleido
Provides-Extra: dev
